gitpicker/__init__.py
gitpicker/gitee.py
gitpicker/github.py
gitpicker/picker.py
gitpicker/version.py
git_picker-0.4.1.dist-info/LICENSE
git_picker-0.4.1.dist-info/METADATA
git_picker-0.4.1.dist-info/WHEEL
git_picker-0.4.1.dist-info/top_level.txt
git_picker-0.4.1.dist-info/RECORD
