Metadata-Version: 2.1
Name: git-picker
Version: 0.4.1
Summary: git picker
Home-page: https://github.com/JiauZhang/git-picker
Author: JiauZhang
Author-email: jiauzhang@163.com
License: MIT
Keywords: GitHub
Classifier: Intended Audience :: Developers
Classifier: License :: OSI Approved :: MIT License
Classifier: Programming Language :: Python :: 3.8
License-File: LICENSE
Requires-Dist: httpx
Requires-Dist: lxml
Requires-Dist: conippets ==0.1.8
